weather_reporter/cli.py
weather_reporter/utils.py
weather_reporter_1.1-1.0.1.dist-info/LICENSE
weather_reporter_1.1-1.0.1.dist-info/METADATA
weather_reporter_1.1-1.0.1.dist-info/WHEEL
weather_reporter_1.1-1.0.1.dist-info/entry_points.txt
weather_reporter_1.1-1.0.1.dist-info/top_level.txt
weather_reporter_1.1-1.0.1.dist-info/RECORD
